<?xml version="1.0" encoding="UTF-8"?>
<ap-stat xmlns="http://www.ruckuswireless.com/AP/PerfDataResp">
<InternetGatewayDevice>
<DeviceInfo X_001392_STATS_INTERVAL="15" X_001392_STATS_INTERVAL_BINS="96" ModelName="VF7811" SerialNumber="180801000148" SoftwareVersion="5.3.3.0.17M" UpTime="20166"/>
<Time CurrentLocalTime="Tue Aug  4 02:08:00 2009"/>
<LANDevice X_001392_LAN_Index="0" LANWLANConfigurationNumberOfEntries="1">
<LANHostConfigManagement IPInterfaceNumberOfEntries="1">
<IPInterface X_001392_IP_INTERFACE_Index="0" X_001392_MGT_MAC="00:1F:41:24:6E:B0" Enable="0" IPInterfaceIPAddress="192.168.2.1"/>
</LANHostConfigManagement>
<WLANConfiguration X_001392_WLAN_Index="0" X_001392_WLAN_NAME="svcp" Enable="1" Channel="108" SSID="V54-246EB0" BeaconType="WPA" Standard="11na" WPAEncryptionModes="AESEncryption" TotalAssociations="2">
<X_001392_WLANStats X_001392_WLAN_STATS_Index="0" X_001392_WLAN_NF="-94" X_001392_WLAN_RX_PKTS="902577" X_001392_WLAN_RX_OCTETS="41902473" X_001392_WLAN_TX_PKTS="10279" X_001392_WLAN_TX_OCTETS="784974"/>
<X_001392_WLANStats X_001392_WLAN_STATS_Index="1" X_001392_WLAN_NF="-94" X_001392_WLAN_RX_PKTS="879242" X_001392_WLAN_RX_OCTETS="40819126" X_001392_WLAN_TX_PKTS="9971" X_001392_WLAN_TX_OCTETS="761753"/>
<X_001392_WLANStats X_001392_WLAN_STATS_Index="2" X_001392_WLAN_NF="-96" X_001392_WLAN_RX_PKTS="833909" X_001392_WLAN_RX_OCTETS="38716436" X_001392_WLAN_TX_PKTS="9420" X_001392_WLAN_TX_OCTETS="720513"/>
<X_001392_WLANStats X_001392_WLAN_STATS_Index="3" X_001392_WLAN_NF="-92" X_001392_WLAN_RX_PKTS="792979" X_001392_WLAN_RX_OCTETS="36813661" X_001392_WLAN_TX_PKTS="8873" X_001392_WLAN_TX_OCTETS="677076"/>
<X_001392_WLANStats X_001392_WLAN_STATS_Index="4" X_001392_WLAN_NF="-90" X_001392_WLAN_RX_PKTS="754047" X_001392_WLAN_RX_OCTETS="35008057" X_001392_WLAN_TX_PKTS="8369" X_001392_WLAN_TX_OCTETS="638989"/>
<X_001392_WLANStats X_001392_WLAN_STATS_Index="5" X_001392_WLAN_NF="-93" X_001392_WLAN_RX_PKTS="722307" X_001392_WLAN_RX_OCTETS="33534492" X_001392_WLAN_TX_PKTS="7923" X_001392_WLAN_TX_OCTETS="604995"/>
<X_001392_WLANStats X_001392_WLAN_STATS_Index="6" X_001392_WLAN_NF="-98" X_001392_WLAN_RX_PKTS="678985" X_001392_WLAN_RX_OCTETS="31528414" X_001392_WLAN_TX_PKTS="7503" X_001392_WLAN_TX_OCTETS="572955"/>
<X_001392_WLANStats X_001392_WLAN_STATS_Index="7" X_001392_WLAN_NF="-92" X_001392_WLAN_RX_PKTS="641901" X_001392_WLAN_RX_OCTETS="29808644" X_001392_WLAN_TX_PKTS="7081" X_001392_WLAN_TX_OCTETS="540641"/>
<X_001392_WLANStats X_001392_WLAN_STATS_Index="8" X_001392_WLAN_NF="-93" X_001392_WLAN_RX_PKTS="591075" X_001392_WLAN_RX_OCTETS="27440487" X_001392_WLAN_TX_PKTS="6661" X_001392_WLAN_TX_OCTETS="508601"/>
<X_001392_WLANStats X_001392_WLAN_STATS_Index="9" X_001392_WLAN_NF="-91" X_001392_WLAN_RX_PKTS="550427" X_001392_WLAN_RX_OCTETS="25557275" X_001392_WLAN_TX_PKTS="6241" X_001392_WLAN_TX_OCTETS="476561"/>
<X_001392_WLANStats X_001392_WLAN_STATS_Index="10" X_001392_WLAN_NF="-96" X_001392_WLAN_RX_PKTS="507997" X_001392_WLAN_RX_OCTETS="23592229" X_001392_WLAN_TX_PKTS="5821" X_001392_WLAN_TX_OCTETS="444521"/>
<X_001392_WLANStats X_001392_WLAN_STATS_Index="11" X_001392_WLAN_NF="-93" X_001392_WLAN_RX_PKTS="466441" X_001392_WLAN_RX_OCTETS="21666329" X_001392_WLAN_TX_PKTS="5401" X_001392_WLAN_TX_OCTETS="412481"/>
<X_001392_WLANStats X_001392_WLAN_STATS_Index="12" X_001392_WLAN_NF="-98" X_001392_WLAN_RX_PKTS="410674" X_001392_WLAN_RX_OCTETS="19083202" X_001392_WLAN_TX_PKTS="4964" X_001392_WLAN_TX_OCTETS="379457"/>
<X_001392_WLANStats X_001392_WLAN_STATS_Index="13" X_001392_WLAN_NF="-90" X_001392_WLAN_RX_PKTS="362458" X_001392_WLAN_RX_OCTETS="16846656" X_001392_WLAN_TX_PKTS="4513" X_001392_WLAN_TX_OCTETS="343470"/>
<X_001392_WLANStats X_001392_WLAN_STATS_Index="14" X_001392_WLAN_NF="-90" X_001392_WLAN_RX_PKTS="328826" X_001392_WLAN_RX_OCTETS="15284252" X_001392_WLAN_TX_PKTS="3942" X_001392_WLAN_TX_OCTETS="300824"/>
<X_001392_WLANStats X_001392_WLAN_STATS_Index="15" X_001392_WLAN_NF="-90" X_001392_WLAN_RX_PKTS="294337" X_001392_WLAN_RX_OCTETS="13682664" X_001392_WLAN_TX_PKTS="3430" X_001392_WLAN_TX_OCTETS="262087"/>
<X_001392_WLANStats X_001392_WLAN_STATS_Index="16" X_001392_WLAN_NF="-90" X_001392_WLAN_RX_PKTS="246489" X_001392_WLAN_RX_OCTETS="11467052" X_001392_WLAN_TX_PKTS="2957" X_001392_WLAN_TX_OCTETS="226358"/>
<X_001392_WLANStats X_001392_WLAN_STATS_Index="17" X_001392_WLAN_NF="-92" X_001392_WLAN_RX_PKTS="215621" X_001392_WLAN_RX_OCTETS="10032631" X_001392_WLAN_TX_PKTS="2530" X_001392_WLAN_TX_OCTETS="193898"/>
<X_001392_WLANStats X_001392_WLAN_STATS_Index="18" X_001392_WLAN_NF="-93" X_001392_WLAN_RX_PKTS="197255" X_001392_WLAN_RX_OCTETS="9173615" X_001392_WLAN_TX_PKTS="2102" X_001392_WLAN_TX_OCTETS="161378"/>
<X_001392_WLANStats X_001392_WLAN_STATS_Index="19" X_001392_WLAN_NF="-92" X_001392_WLAN_RX_PKTS="146715" X_001392_WLAN_RX_OCTETS="6832214" X_001392_WLAN_TX_PKTS="1675" X_001392_WLAN_TX_OCTETS="128918"/>
<X_001392_WLANStats X_001392_WLAN_STATS_Index="20" X_001392_WLAN_NF="-90" X_001392_WLAN_RX_PKTS="97692" X_001392_WLAN_RX_OCTETS="4548289" X_001392_WLAN_TX_PKTS="1247" X_001392_WLAN_TX_OCTETS="96398"/>
<X_001392_WLANStats X_001392_WLAN_STATS_Index="21" X_001392_WLAN_NF="-89" X_001392_WLAN_RX_PKTS="61447" X_001392_WLAN_RX_OCTETS="2864824" X_001392_WLAN_TX_PKTS="820" X_001392_WLAN_TX_OCTETS="63938"/>
<X_001392_WLANStats X_001392_WLAN_STATS_Index="22" X_001392_WLAN_NF="-88" X_001392_WLAN_RX_PKTS="23244" X_001392_WLAN_RX_OCTETS="1090578" X_001392_WLAN_TX_PKTS="322" X_001392_WLAN_TX_OCTETS="26650"/>
<AssociatedDevice X_001392_STA_Index="0" AssociatedDeviceMACAddress="00:22:7f:0f:87:e8" X_001392_STA_NUM_ETHERNET="0">
<X_001392_ClientStats X_001392_STA_STATS_Index="0" X_001392_STA_TX_RSSI="82" X_001392_STA_THROUGHPUT_EST="222150" X_001392_STA_RX_PKTS="134905" X_001392_STA_TX_PKTS_XMIT="7" X_001392_STA_TX_PKTS_QUEUED="0" X_001392_STA_TX_PKTS_DROP_OVERFLOW="0" X_001392_STA_TX_PKTS_DROP_XRETRIES="0" X_001392_STA_TX_PKTS_DROP_OVERDUE="0"/>
<X_001392_ClientStats X_001392_STA_STATS_Index="1" X_001392_STA_TX_RSSI="83" X_001392_STA_THROUGHPUT_EST="232103" X_001392_STA_RX_PKTS="132645" X_001392_STA_TX_PKTS_XMIT="7" X_001392_STA_TX_PKTS_QUEUED="0" X_001392_STA_TX_PKTS_DROP_OVERFLOW="0" X_001392_STA_TX_PKTS_DROP_XRETRIES="0" X_001392_STA_TX_PKTS_DROP_OVERDUE="0"/>
<X_001392_ClientStats X_001392_STA_STATS_Index="2" X_001392_STA_TX_RSSI="85" X_001392_STA_THROUGHPUT_EST="227555" X_001392_STA_RX_PKTS="128830" X_001392_STA_TX_PKTS_XMIT="7" X_001392_STA_TX_PKTS_QUEUED="0" X_001392_STA_TX_PKTS_DROP_OVERFLOW="0" X_001392_STA_TX_PKTS_DROP_XRETRIES="0" X_001392_STA_TX_PKTS_DROP_OVERDUE="0"/>
<X_001392_ClientStats X_001392_STA_STATS_Index="3" X_001392_STA_TX_RSSI="84" X_001392_STA_THROUGHPUT_EST="229221" X_001392_STA_RX_PKTS="125020" X_001392_STA_TX_PKTS_XMIT="7" X_001392_STA_TX_PKTS_QUEUED="0" X_001392_STA_TX_PKTS_DROP_OVERFLOW="0" X_001392_STA_TX_PKTS_DROP_XRETRIES="0" X_001392_STA_TX_PKTS_DROP_OVERDUE="0"/>
<X_001392_ClientStats X_001392_STA_STATS_Index="4" X_001392_STA_TX_RSSI="85" X_001392_STA_THROUGHPUT_EST="235734" X_001392_STA_RX_PKTS="121209" X_001392_STA_TX_PKTS_XMIT="7" X_001392_STA_TX_PKTS_QUEUED="0" X_001392_STA_TX_PKTS_DROP_OVERFLOW="0" X_001392_STA_TX_PKTS_DROP_XRETRIES="0" X_001392_STA_TX_PKTS_DROP_OVERDUE="0"/>
<X_001392_ClientStats X_001392_STA_STATS_Index="5" X_001392_STA_TX_RSSI="85" X_001392_STA_THROUGHPUT_EST="227448" X_001392_STA_RX_PKTS="117399" X_001392_STA_TX_PKTS_XMIT="7" X_001392_STA_TX_PKTS_QUEUED="0" X_001392_STA_TX_PKTS_DROP_OVERFLOW="0" X_001392_STA_TX_PKTS_DROP_XRETRIES="0" X_001392_STA_TX_PKTS_DROP_OVERDUE="0"/>
<X_001392_ClientStats X_001392_STA_STATS_Index="6" X_001392_STA_TX_RSSI="84" X_001392_STA_THROUGHPUT_EST="235118" X_001392_STA_RX_PKTS="111804" X_001392_STA_TX_PKTS_XMIT="7" X_001392_STA_TX_PKTS_QUEUED="0" X_001392_STA_TX_PKTS_DROP_OVERFLOW="0" X_001392_STA_TX_PKTS_DROP_XRETRIES="0" X_001392_STA_TX_PKTS_DROP_OVERDUE="0"/>
<X_001392_ClientStats X_001392_STA_STATS_Index="7" X_001392_STA_TX_RSSI="84" X_001392_STA_THROUGHPUT_EST="232130" X_001392_STA_RX_PKTS="107989" X_001392_STA_TX_PKTS_XMIT="7" X_001392_STA_TX_PKTS_QUEUED="0" X_001392_STA_TX_PKTS_DROP_OVERFLOW="0" X_001392_STA_TX_PKTS_DROP_XRETRIES="0" X_001392_STA_TX_PKTS_DROP_OVERDUE="0"/>
<X_001392_ClientStats X_001392_STA_STATS_Index="8" X_001392_STA_TX_RSSI="84" X_001392_STA_THROUGHPUT_EST="225242" X_001392_STA_RX_PKTS="104179" X_001392_STA_TX_PKTS_XMIT="7" X_001392_STA_TX_PKTS_QUEUED="0" X_001392_STA_TX_PKTS_DROP_OVERFLOW="0" X_001392_STA_TX_PKTS_DROP_XRETRIES="0" X_001392_STA_TX_PKTS_DROP_OVERDUE="0"/>
<X_001392_ClientStats X_001392_STA_STATS_Index="9" X_001392_STA_TX_RSSI="85" X_001392_STA_THROUGHPUT_EST="221371" X_001392_STA_RX_PKTS="100368" X_001392_STA_TX_PKTS_XMIT="7" X_001392_STA_TX_PKTS_QUEUED="0" X_001392_STA_TX_PKTS_DROP_OVERFLOW="0" X_001392_STA_TX_PKTS_DROP_XRETRIES="0" X_001392_STA_TX_PKTS_DROP_OVERDUE="0"/>
<X_001392_ClientStats X_001392_STA_STATS_Index="10" X_001392_STA_TX_RSSI="81" X_001392_STA_THROUGHPUT_EST="198301" X_001392_STA_RX_PKTS="94773" X_001392_STA_TX_PKTS_XMIT="7" X_001392_STA_TX_PKTS_QUEUED="0" X_001392_STA_TX_PKTS_DROP_OVERFLOW="0" X_001392_STA_TX_PKTS_DROP_XRETRIES="0" X_001392_STA_TX_PKTS_DROP_OVERDUE="0"/>
<X_001392_ClientStats X_001392_STA_STATS_Index="11" X_001392_STA_TX_RSSI="85" X_001392_STA_THROUGHPUT_EST="220646" X_001392_STA_RX_PKTS="88282" X_001392_STA_TX_PKTS_XMIT="7" X_001392_STA_TX_PKTS_QUEUED="0" X_001392_STA_TX_PKTS_DROP_OVERFLOW="0" X_001392_STA_TX_PKTS_DROP_XRETRIES="0" X_001392_STA_TX_PKTS_DROP_OVERDUE="0"/>
<X_001392_ClientStats X_001392_STA_STATS_Index="12" X_001392_STA_TX_RSSI="75" X_001392_STA_THROUGHPUT_EST="197535" X_001392_STA_RX_PKTS="71286" X_001392_STA_TX_PKTS_XMIT="7" X_001392_STA_TX_PKTS_QUEUED="0" X_001392_STA_TX_PKTS_DROP_OVERFLOW="0" X_001392_STA_TX_PKTS_DROP_XRETRIES="0" X_001392_STA_TX_PKTS_DROP_OVERDUE="0"/>
<X_001392_ClientStats X_001392_STA_STATS_Index="13" X_001392_STA_TX_RSSI="85" X_001392_STA_THROUGHPUT_EST="194120" X_001392_STA_RX_PKTS="62809" X_001392_STA_TX_PKTS_XMIT="7" X_001392_STA_TX_PKTS_QUEUED="0" X_001392_STA_TX_PKTS_DROP_OVERFLOW="0" X_001392_STA_TX_PKTS_DROP_XRETRIES="0" X_001392_STA_TX_PKTS_DROP_OVERDUE="0"/>
<X_001392_ClientStats X_001392_STA_STATS_Index="14" X_001392_STA_TX_RSSI="84" X_001392_STA_THROUGHPUT_EST="195504" X_001392_STA_RX_PKTS="57213" X_001392_STA_TX_PKTS_XMIT="7" X_001392_STA_TX_PKTS_QUEUED="0" X_001392_STA_TX_PKTS_DROP_OVERFLOW="0" X_001392_STA_TX_PKTS_DROP_XRETRIES="0" X_001392_STA_TX_PKTS_DROP_OVERDUE="0"/>
<X_001392_ClientStats X_001392_STA_STATS_Index="15" X_001392_STA_TX_RSSI="86" X_001392_STA_THROUGHPUT_EST="162000" X_001392_STA_RX_PKTS="53399" X_001392_STA_TX_PKTS_XMIT="7" X_001392_STA_TX_PKTS_QUEUED="0" X_001392_STA_TX_PKTS_DROP_OVERFLOW="0" X_001392_STA_TX_PKTS_DROP_XRETRIES="0" X_001392_STA_TX_PKTS_DROP_OVERDUE="0"/>
<X_001392_ClientStats X_001392_STA_STATS_Index="16" X_001392_STA_TX_RSSI="84" X_001392_STA_THROUGHPUT_EST="160566" X_001392_STA_RX_PKTS="49589" X_001392_STA_TX_PKTS_XMIT="7" X_001392_STA_TX_PKTS_QUEUED="0" X_001392_STA_TX_PKTS_DROP_OVERFLOW="0" X_001392_STA_TX_PKTS_DROP_XRETRIES="0" X_001392_STA_TX_PKTS_DROP_OVERDUE="0"/>
<X_001392_ClientStats X_001392_STA_STATS_Index="17" X_001392_STA_TX_RSSI="85" X_001392_STA_THROUGHPUT_EST="152689" X_001392_STA_RX_PKTS="45778" X_001392_STA_TX_PKTS_XMIT="7" X_001392_STA_TX_PKTS_QUEUED="0" X_001392_STA_TX_PKTS_DROP_OVERFLOW="0" X_001392_STA_TX_PKTS_DROP_XRETRIES="0" X_001392_STA_TX_PKTS_DROP_OVERDUE="0"/>
<X_001392_ClientStats X_001392_STA_STATS_Index="18" X_001392_STA_TX_RSSI="85" X_001392_STA_THROUGHPUT_EST="125808" X_001392_STA_RX_PKTS="41967" X_001392_STA_TX_PKTS_XMIT="7" X_001392_STA_TX_PKTS_QUEUED="0" X_001392_STA_TX_PKTS_DROP_OVERFLOW="0" X_001392_STA_TX_PKTS_DROP_XRETRIES="0" X_001392_STA_TX_PKTS_DROP_OVERDUE="0"/>
<X_001392_ClientStats X_001392_STA_STATS_Index="19" X_001392_STA_TX_RSSI="85" X_001392_STA_THROUGHPUT_EST="136387" X_001392_STA_RX_PKTS="38155" X_001392_STA_TX_PKTS_XMIT="7" X_001392_STA_TX_PKTS_QUEUED="0" X_001392_STA_TX_PKTS_DROP_OVERFLOW="0" X_001392_STA_TX_PKTS_DROP_XRETRIES="0" X_001392_STA_TX_PKTS_DROP_OVERDUE="0"/>
<X_001392_ClientStats X_001392_STA_STATS_Index="20" X_001392_STA_TX_RSSI="84" X_001392_STA_THROUGHPUT_EST="161142" X_001392_STA_RX_PKTS="32560" X_001392_STA_TX_PKTS_XMIT="7" X_001392_STA_TX_PKTS_QUEUED="0" X_001392_STA_TX_PKTS_DROP_OVERFLOW="0" X_001392_STA_TX_PKTS_DROP_XRETRIES="0" X_001392_STA_TX_PKTS_DROP_OVERDUE="0"/>
<X_001392_ClientStats X_001392_STA_STATS_Index="21" X_001392_STA_TX_RSSI="83" X_001392_STA_THROUGHPUT_EST="160213" X_001392_STA_RX_PKTS="24286" X_001392_STA_TX_PKTS_XMIT="7" X_001392_STA_TX_PKTS_QUEUED="0" X_001392_STA_TX_PKTS_DROP_OVERFLOW="0" X_001392_STA_TX_PKTS_DROP_XRETRIES="0" X_001392_STA_TX_PKTS_DROP_OVERDUE="0"/>
<X_001392_ClientStats X_001392_STA_STATS_Index="22" X_001392_STA_TX_RSSI="81" X_001392_STA_THROUGHPUT_EST="161270" X_001392_STA_RX_PKTS="16009" X_001392_STA_TX_PKTS_XMIT="7" X_001392_STA_TX_PKTS_QUEUED="0" X_001392_STA_TX_PKTS_DROP_OVERFLOW="0" X_001392_STA_TX_PKTS_DROP_XRETRIES="0" X_001392_STA_TX_PKTS_DROP_OVERDUE="0"/>
</AssociatedDevice>
<AssociatedDevice X_001392_STA_Index="1" AssociatedDeviceMACAddress="00:22:7f:0f:88:38" X_001392_STA_NUM_ETHERNET="1">
<X_001392_STA_ETHER_MAC X_001392_STA_ETHER_Index="0" X_001392_STA_ETHER_ADDR="00:01:4a:09:d3:bc"/>
<X_001392_ClientStats X_001392_STA_STATS_Index="0" X_001392_STA_TX_RSSI="84" X_001392_STA_THROUGHPUT_EST="80564" X_001392_STA_RX_PKTS="767668" X_001392_STA_TX_PKTS_XMIT="2" X_001392_STA_TX_PKTS_QUEUED="0" X_001392_STA_TX_PKTS_DROP_OVERFLOW="0" X_001392_STA_TX_PKTS_DROP_XRETRIES="0" X_001392_STA_TX_PKTS_DROP_OVERDUE="0"/>
<X_001392_ClientStats X_001392_STA_STATS_Index="1" X_001392_STA_TX_RSSI="85" X_001392_STA_THROUGHPUT_EST="79864" X_001392_STA_RX_PKTS="746591" X_001392_STA_TX_PKTS_XMIT="2" X_001392_STA_TX_PKTS_QUEUED="0" X_001392_STA_TX_PKTS_DROP_OVERFLOW="0" X_001392_STA_TX_PKTS_DROP_XRETRIES="0" X_001392_STA_TX_PKTS_DROP_OVERDUE="0"/>
<X_001392_ClientStats X_001392_STA_STATS_Index="2" X_001392_STA_TX_RSSI="87" X_001392_STA_THROUGHPUT_EST="79627" X_001392_STA_RX_PKTS="705073" X_001392_STA_TX_PKTS_XMIT="2" X_001392_STA_TX_PKTS_QUEUED="0" X_001392_STA_TX_PKTS_DROP_OVERFLOW="0" X_001392_STA_TX_PKTS_DROP_XRETRIES="0" X_001392_STA_TX_PKTS_DROP_OVERDUE="0"/>
<X_001392_ClientStats X_001392_STA_STATS_Index="3" X_001392_STA_TX_RSSI="85" X_001392_STA_THROUGHPUT_EST="80181" X_001392_STA_RX_PKTS="667953" X_001392_STA_TX_PKTS_XMIT="2" X_001392_STA_TX_PKTS_QUEUED="0" X_001392_STA_TX_PKTS_DROP_OVERFLOW="0" X_001392_STA_TX_PKTS_DROP_XRETRIES="0" X_001392_STA_TX_PKTS_DROP_OVERDUE="0"/>
<X_001392_ClientStats X_001392_STA_STATS_Index="4" X_001392_STA_TX_RSSI="86" X_001392_STA_THROUGHPUT_EST="79038" X_001392_STA_RX_PKTS="632832" X_001392_STA_TX_PKTS_XMIT="2" X_001392_STA_TX_PKTS_QUEUED="0" X_001392_STA_TX_PKTS_DROP_OVERFLOW="0" X_001392_STA_TX_PKTS_DROP_XRETRIES="0" X_001392_STA_TX_PKTS_DROP_OVERDUE="0"/>
<X_001392_ClientStats X_001392_STA_STATS_Index="5" X_001392_STA_TX_RSSI="86" X_001392_STA_THROUGHPUT_EST="80068" X_001392_STA_RX_PKTS="604902" X_001392_STA_TX_PKTS_XMIT="2" X_001392_STA_TX_PKTS_QUEUED="0" X_001392_STA_TX_PKTS_DROP_OVERFLOW="0" X_001392_STA_TX_PKTS_DROP_XRETRIES="0" X_001392_STA_TX_PKTS_DROP_OVERDUE="0"/>
<X_001392_ClientStats X_001392_STA_STATS_Index="6" X_001392_STA_TX_RSSI="88" X_001392_STA_THROUGHPUT_EST="80362" X_001392_STA_RX_PKTS="567175" X_001392_STA_TX_PKTS_XMIT="2" X_001392_STA_TX_PKTS_QUEUED="0" X_001392_STA_TX_PKTS_DROP_OVERFLOW="0" X_001392_STA_TX_PKTS_DROP_XRETRIES="0" X_001392_STA_TX_PKTS_DROP_OVERDUE="0"/>
<X_001392_ClientStats X_001392_STA_STATS_Index="7" X_001392_STA_TX_RSSI="87" X_001392_STA_THROUGHPUT_EST="80523" X_001392_STA_RX_PKTS="533906" X_001392_STA_TX_PKTS_XMIT="2" X_001392_STA_TX_PKTS_QUEUED="0" X_001392_STA_TX_PKTS_DROP_OVERFLOW="0" X_001392_STA_TX_PKTS_DROP_XRETRIES="0" X_001392_STA_TX_PKTS_DROP_OVERDUE="0"/>
<X_001392_ClientStats X_001392_STA_STATS_Index="8" X_001392_STA_TX_RSSI="86" X_001392_STA_THROUGHPUT_EST="80336" X_001392_STA_RX_PKTS="486891" X_001392_STA_TX_PKTS_XMIT="2" X_001392_STA_TX_PKTS_QUEUED="0" X_001392_STA_TX_PKTS_DROP_OVERFLOW="0" X_001392_STA_TX_PKTS_DROP_XRETRIES="0" X_001392_STA_TX_PKTS_DROP_OVERDUE="0"/>
<X_001392_ClientStats X_001392_STA_STATS_Index="9" X_001392_STA_TX_RSSI="87" X_001392_STA_THROUGHPUT_EST="81000" X_001392_STA_RX_PKTS="450053" X_001392_STA_TX_PKTS_XMIT="2" X_001392_STA_TX_PKTS_QUEUED="0" X_001392_STA_TX_PKTS_DROP_OVERFLOW="0" X_001392_STA_TX_PKTS_DROP_XRETRIES="0" X_001392_STA_TX_PKTS_DROP_OVERDUE="0"/>
<X_001392_ClientStats X_001392_STA_STATS_Index="10" X_001392_STA_TX_RSSI="90" X_001392_STA_THROUGHPUT_EST="80338" X_001392_STA_RX_PKTS="413218" X_001392_STA_TX_PKTS_XMIT="2" X_001392_STA_TX_PKTS_QUEUED="0" X_001392_STA_TX_PKTS_DROP_OVERFLOW="0" X_001392_STA_TX_PKTS_DROP_XRETRIES="0" X_001392_STA_TX_PKTS_DROP_OVERDUE="0"/>
<X_001392_ClientStats X_001392_STA_STATS_Index="11" X_001392_STA_TX_RSSI="86" X_001392_STA_THROUGHPUT_EST="80514" X_001392_STA_RX_PKTS="378153" X_001392_STA_TX_PKTS_XMIT="2" X_001392_STA_TX_PKTS_QUEUED="0" X_001392_STA_TX_PKTS_DROP_OVERFLOW="0" X_001392_STA_TX_PKTS_DROP_XRETRIES="0" X_001392_STA_TX_PKTS_DROP_OVERDUE="0"/>
<X_001392_ClientStats X_001392_STA_STATS_Index="12" X_001392_STA_TX_RSSI="85" X_001392_STA_THROUGHPUT_EST="80310" X_001392_STA_RX_PKTS="339385" X_001392_STA_TX_PKTS_XMIT="2" X_001392_STA_TX_PKTS_QUEUED="0" X_001392_STA_TX_PKTS_DROP_OVERFLOW="0" X_001392_STA_TX_PKTS_DROP_XRETRIES="0" X_001392_STA_TX_PKTS_DROP_OVERDUE="0"/>
<X_001392_ClientStats X_001392_STA_STATS_Index="13" X_001392_STA_TX_RSSI="88" X_001392_STA_THROUGHPUT_EST="76736" X_001392_STA_RX_PKTS="299643" X_001392_STA_TX_PKTS_XMIT="2" X_001392_STA_TX_PKTS_QUEUED="0" X_001392_STA_TX_PKTS_DROP_OVERFLOW="0" X_001392_STA_TX_PKTS_DROP_XRETRIES="0" X_001392_STA_TX_PKTS_DROP_OVERDUE="0"/>
<X_001392_ClientStats X_001392_STA_STATS_Index="14" X_001392_STA_TX_RSSI="84" X_001392_STA_THROUGHPUT_EST="52888" X_001392_STA_RX_PKTS="271607" X_001392_STA_TX_PKTS_XMIT="2" X_001392_STA_TX_PKTS_QUEUED="0" X_001392_STA_TX_PKTS_DROP_OVERFLOW="0" X_001392_STA_TX_PKTS_DROP_XRETRIES="0" X_001392_STA_TX_PKTS_DROP_OVERDUE="0"/>
<X_001392_ClientStats X_001392_STA_STATS_Index="15" X_001392_STA_TX_RSSI="87" X_001392_STA_THROUGHPUT_EST="51300" X_001392_STA_RX_PKTS="240932" X_001392_STA_TX_PKTS_XMIT="2" X_001392_STA_TX_PKTS_QUEUED="0" X_001392_STA_TX_PKTS_DROP_OVERFLOW="0" X_001392_STA_TX_PKTS_DROP_XRETRIES="0" X_001392_STA_TX_PKTS_DROP_OVERDUE="0"/>
<X_001392_ClientStats X_001392_STA_STATS_Index="16" X_001392_STA_TX_RSSI="83" X_001392_STA_THROUGHPUT_EST="54000" X_001392_STA_RX_PKTS="196895" X_001392_STA_TX_PKTS_XMIT="2" X_001392_STA_TX_PKTS_QUEUED="0" X_001392_STA_TX_PKTS_DROP_OVERFLOW="0" X_001392_STA_TX_PKTS_DROP_XRETRIES="0" X_001392_STA_TX_PKTS_DROP_OVERDUE="0"/>
<X_001392_ClientStats X_001392_STA_STATS_Index="17" X_001392_STA_TX_RSSI="89" X_001392_STA_THROUGHPUT_EST="54000" X_001392_STA_RX_PKTS="169837" X_001392_STA_TX_PKTS_XMIT="2" X_001392_STA_TX_PKTS_QUEUED="0" X_001392_STA_TX_PKTS_DROP_OVERFLOW="0" X_001392_STA_TX_PKTS_DROP_XRETRIES="0" X_001392_STA_TX_PKTS_DROP_OVERDUE="0"/>
<X_001392_ClientStats X_001392_STA_STATS_Index="18" X_001392_STA_TX_RSSI="87" X_001392_STA_THROUGHPUT_EST="54000" X_001392_STA_RX_PKTS="155282" X_001392_STA_TX_PKTS_XMIT="2" X_001392_STA_TX_PKTS_QUEUED="0" X_001392_STA_TX_PKTS_DROP_OVERFLOW="0" X_001392_STA_TX_PKTS_DROP_XRETRIES="0" X_001392_STA_TX_PKTS_DROP_OVERDUE="0"/>
<X_001392_ClientStats X_001392_STA_STATS_Index="19" X_001392_STA_TX_RSSI="87" X_001392_STA_THROUGHPUT_EST="53004" X_001392_STA_RX_PKTS="108554" X_001392_STA_TX_PKTS_XMIT="2" X_001392_STA_TX_PKTS_QUEUED="0" X_001392_STA_TX_PKTS_DROP_OVERFLOW="0" X_001392_STA_TX_PKTS_DROP_XRETRIES="0" X_001392_STA_TX_PKTS_DROP_OVERDUE="0"/>
<X_001392_ClientStats X_001392_STA_STATS_Index="20" X_001392_STA_TX_RSSI="82" X_001392_STA_THROUGHPUT_EST="39137" X_001392_STA_RX_PKTS="65126" X_001392_STA_TX_PKTS_XMIT="2" X_001392_STA_TX_PKTS_QUEUED="0" X_001392_STA_TX_PKTS_DROP_OVERFLOW="0" X_001392_STA_TX_PKTS_DROP_XRETRIES="0" X_001392_STA_TX_PKTS_DROP_OVERDUE="0"/>
<X_001392_ClientStats X_001392_STA_STATS_Index="21" X_001392_STA_TX_RSSI="83" X_001392_STA_THROUGHPUT_EST="36926" X_001392_STA_RX_PKTS="37155" X_001392_STA_TX_PKTS_XMIT="2" X_001392_STA_TX_PKTS_QUEUED="0" X_001392_STA_TX_PKTS_DROP_OVERFLOW="0" X_001392_STA_TX_PKTS_DROP_XRETRIES="0" X_001392_STA_TX_PKTS_DROP_OVERDUE="0"/>
<X_001392_ClientStats X_001392_STA_STATS_Index="22" X_001392_STA_TX_RSSI="81" X_001392_STA_THROUGHPUT_EST="38127" X_001392_STA_RX_PKTS="7229" X_001392_STA_TX_PKTS_XMIT="2" X_001392_STA_TX_PKTS_QUEUED="0" X_001392_STA_TX_PKTS_DROP_OVERFLOW="0" X_001392_STA_TX_PKTS_DROP_XRETRIES="0" X_001392_STA_TX_PKTS_DROP_OVERDUE="0"/>
</AssociatedDevice>
</WLANConfiguration>
</LANDevice>
</InternetGatewayDevice>
<ResponseStatus Code="0" Msg="Success"/>
</ap-stat>
